constants.py
protocolpro.py
specs.py
protocolpro-0.3.dist-info/LICENSE.txt
protocolpro-0.3.dist-info/METADATA
protocolpro-0.3.dist-info/WHEEL
protocolpro-0.3.dist-info/entry_points.txt
protocolpro-0.3.dist-info/top_level.txt
protocolpro-0.3.dist-info/RECORD
