Metadata-Version: 2.1
Name: protocolpro
Version: 0.3
Summary: ASCII and Unicode Header Generator for Network Protocols
Author-email: Luis MartinGarcia <luis@luismg.com>, Tom Pusateri <pusateri@bangj.com>, Leytou <hi_litao@163.com>
Project-URL: Homepage, https://github.com/leytou/protocolpro
Project-URL: Bug Tracker, https://github.com/leytou/protocolpro/issues
Classifier: Programming Language :: Python :: 3
Classifier: License :: OSI Approved :: GNU General Public License v3 or later (GPLv3+)
Classifier: Operating System :: OS Independent
Requires-Python: >=3.7
License-File: LICENSE.txt
